[
  {
    "Function_ID": 1,
    "Function_CategaryCode": 22,
    "Function_CategaryName": "生活資訊",
    "Function_Icon": "category2_news",
    "Function_Name": "新聞",
    "Function_URL": "index.html",
    "Function_IsActive": 1
  },
  {
    "Function_ID": 2,
    "Function_CategaryCode": 22,
    "Function_CategaryName": "生活資訊",
    "Function_Icon": "category2_1dollar",
    "Function_Name": "一元搶購",
    "Function_URL": "offers/offers_one.html",
    "Function_IsActive": 1
  },
  {
    "Function_ID": 3,
    "Function_CategaryCode": 23,
    "Function_CategaryName": "娛樂放鬆",
    "Function_Icon": "category2_games",
    "Function_Name": "遊戲",
    "Function_URL": "game/game.html",
    "Function_IsActive": 1
  },
  {
    "Function_ID": 4,
    "Function_CategaryCode": 22,
    "Function_CategaryName": "生活資訊",
    "Function_Icon": "category2_thunder",
    "Function_Name": "彩蛋",
    "Function_URL": "index.html",
    "Function_IsActive": 1
  },
  {
    "Function_ID": 5,
    "Function_CategaryCode": 21,
    "Function_CategaryName": "饗食達人",
    "Function_Icon": "category2_sushi",
    "Function_Name": "壽司",
    "Function_URL": "index.html",
    "Function_IsActive": 1
  },
  {
    "Function_ID": 6,
    "Function_CategaryCode": 21,
    "Function_CategaryName": "饗食達人",
    "Function_Icon": "category2_coffee",
    "Function_Name": "咖啡",
    "Function_URL": "index.html",
    "Function_IsActive": 1
  },
  {
    "Function_ID": 7,
    "Function_CategaryCode": 21,
    "Function_CategaryName": "饗食達人",
    "Function_Icon": "category2_tea",
    "Function_Name": "茶藝",
    "Function_URL": "index.html",
    "Function_IsActive": 1
  },
  {
    "Function_ID": 8,
    "Function_CategaryCode": 21,
    "Function_CategaryName": "饗食達人",
    "Function_Icon": "category2_orgaic",
    "Function_Name": "有機",
    "Function_URL": "index.html",
    "Function_IsActive": 1
  },
  {
    "Function_ID": 9,
    "Function_CategaryCode": 21,
    "Function_CategaryName": "饗食達人",
    "Function_Icon": "category2_a5",
    "Function_Name": "和牛",
    "Function_URL": "index.html",
    "Function_IsActive": 1
  },
  {
    "Function_ID": 10,
    "Function_CategaryCode": 21,
    "Function_CategaryName": "饗食達人",
    "Function_Icon": "category2_agriculture",
    "Function_Name": "神農獎",
    "Function_URL": "index.html",
    "Function_IsActive": 1
  },
  {
    "Function_ID": 11,
    "Function_CategaryCode": 20,
    "Function_CategaryName": "美麗生活",
    "Function_Icon": "category2_fasion",
    "Function_Name": "時尚精品",
    "Function_URL": "index.html",
    "Function_IsActive": 1
  },
  {
    "Function_ID": 12,
    "Function_CategaryCode": 20,
    "Function_CategaryName": "美麗生活",
    "Function_Icon": "category2_makeups",
    "Function_Name": "美妝",
    "Function_URL": "index.html",
    "Function_IsActive": 1
  },
  {
    "Function_ID": 13,
    "Function_CategaryCode": 20,
    "Function_CategaryName": "美麗生活",
    "Function_Icon": "category2_haircut",
    "Function_Name": "美髮",
    "Function_URL": "index.html",
    "Function_IsActive": 1
  },
  {
    "Function_ID": 14,
    "Function_CategaryCode": 20,
    "Function_CategaryName": "美麗生活",
    "Function_Icon": "category2_nail",
    "Function_Name": "美甲",
    "Function_URL": "index.html",
    "Function_IsActive": 1
  },
  {
    "Function_ID": 15,
    "Function_CategaryCode": 20,
    "Function_CategaryName": "美麗生活",
    "Function_Icon": "category2_cosmetology",
    "Function_Name": "醫美",
    "Function_URL": "index.html",
    "Function_IsActive": 1
  },
  {
    "Function_ID": 16,
    "Function_CategaryCode": 20,
    "Function_CategaryName": "美麗生活",
    "Function_Icon": "category2_feet",
    "Function_Name": "足療",
    "Function_URL": "index.html",
    "Function_IsActive": 1
  },
  {
    "Function_ID": 17,
    "Function_CategaryCode": 20,
    "Function_CategaryName": "美麗生活",
    "Function_Icon": "category2_spa",
    "Function_Name": "SPA",
    "Function_URL": "index.html",
    "Function_IsActive": 1
  },
  {
    "Function_ID": 18,
    "Function_CategaryCode": 20,
    "Function_CategaryName": "美麗生活",
    "Function_Icon": "category2_femaleshoes",
    "Function_Name": "女鞋",
    "Function_URL": "index.html",
    "Function_IsActive": 1
  },
  {
    "Function_ID": 19,
    "Function_CategaryCode": 20,
    "Function_CategaryName": "美麗生活",
    "Function_Icon": "category2_femalebag",
    "Function_Name": "女包",
    "Function_URL": "index.html",
    "Function_IsActive": 1
  },
  {
    "Function_ID": 20,
    "Function_CategaryCode": 20,
    "Function_CategaryName": "美麗生活",
    "Function_Icon": "category2_car",
    "Function_Name": "汽車百貨",
    "Function_URL": "index.html",
    "Function_IsActive": 1
  },
  {
    "Function_ID": 21,
    "Function_CategaryCode": 24,
    "Function_CategaryName": "交通服務",
    "Function_Icon": "category3_qrcode",
    "Function_Name": "乘車碼",
    "Function_URL": "",
    "Function_IsActive": 1
  },
  {
    "Function_ID": 22,
    "Function_CategaryCode": 22,
    "Function_CategaryName": "生活資訊",
    "Function_Icon": "category3_payment",
    "Function_Name": "繳費",
    "Function_URL": "",
    "Function_IsActive": 0
  }
]
